hwc_chw_ndarray_conversion.py
hwc_chw_ndarray_conversion-0.1.0a0.dist-info/licenses/LICENSE
hwc_chw_ndarray_conversion-0.1.0a0.dist-info/METADATA
hwc_chw_ndarray_conversion-0.1.0a0.dist-info/WHEEL
hwc_chw_ndarray_conversion-0.1.0a0.dist-info/top_level.txt
hwc_chw_ndarray_conversion-0.1.0a0.dist-info/RECORD
