Metadata-Version: 2.4
Name: hwc-chw-ndarray-conversion
Version: 0.1.0a0
Summary: Explicit, contiguous HWC <-> CHW ndarray conversion.
Author-email: Jifeng Wu <jifengwu2k@gmail.com>
License-Expression: MIT
Project-URL: Homepage, https://github.com/jifengwu2k/hwc-chw-ndarray-conversion
Project-URL: Bug Tracker, https://github.com/jifengwu2k/hwc-chw-ndarray-conversion/issues
Classifier: Programming Language :: Python :: 2
Classifier: Programming Language :: Python :: 3
Classifier: Operating System :: OS Independent
Requires-Python: >=2
License-File: LICENSE
Requires-Dist: numpy
Dynamic: license-file
